google_manager_libreria/__init__.py
google_manager_libreria-0.1.0.dist-info/METADATA
google_manager_libreria-0.1.0.dist-info/WHEEL
google_manager_libreria-0.1.0.dist-info/top_level.txt
google_manager_libreria-0.1.0.dist-info/RECORD
