Metadata-Version: 2.1
Name: google_manager_libreria
Version: 0.1.0
Summary: manejo del paquete google mails,hojas de calculodrive 
Author: Jose parodi
Author-email: Jose Parodi <developers@consultoraparodi.com.ar>
Project-URL: Homepage, https://github.com/consultoraparodi/google_manager_libreria
Project-URL: Bug Tracker, https://github.com/consultoraparodi/google_manager_libreria/issues
Classifier: Programming Language :: Python :: 3
Classifier: License :: OSI Approved :: MIT License
Classifier: Operating System :: OS Independent
Requires-Python: >=3.12
Requires-Dist: requests
Provides-Extra: cli
Requires-Dist: rich; extra == "cli"
Requires-Dist: click; extra == "cli"
Provides-Extra: gui
Requires-Dist: PyQt5; extra == "gui"
